[{"date":"2015-05-19","nightly":16,"aurora":32,"beta":652,"release":1072},{"date":"2015-05-20","nightly":10,"aurora":38,"beta":701,"release":970},{"date":"2015-05-21","nightly":12,"aurora":34,"beta":509,"release":998},{"date":"2015-05-22","nightly":9,"aurora":33,"beta":596,"release":912},{"date":"2015-05-23","nightly":19,"aurora":26,"beta":442,"release":658},{"date":"2015-05-24","nightly":30,"aurora":28,"beta":342,"release":635},{"date":"2015-05-25","nightly":16,"aurora":29,"beta":623,"release":925},{"date":"2015-05-26","nightly":3,"aurora":44,"beta":661,"release":1048},{"date":"2015-05-27","nightly":12,"aurora":50,"beta":692,"release":1032},{"date":"2015-05-28","nightly":104,"aurora":36,"beta":609,"release":1092},{"date":"2015-05-29","nightly":82,"aurora":39,"beta":1187,"release":937},{"date":"2015-05-30","nightly":45,"aurora":49,"beta":1992,"release":638},{"date":"2015-05-31","nightly":51,"aurora":36,"beta":2048,"release":685},{"date":"2015-06-01","nightly":46,"aurora":44,"beta":2465,"release":1046},{"date":"2015-06-02","nightly":59,"aurora":29,"beta":2229,"release":989},{"date":"2015-06-03","nightly":57,"aurora":23,"beta":2498,"release":1052},{"date":"2015-06-04","nightly":64,"aurora":33,"beta":2558,"release":1039},{"date":"2015-06-05","nightly":44,"aurora":35,"beta":2542,"release":1090},{"date":"2015-06-06","nightly":38,"aurora":42,"beta":2454,"release":622},{"date":"2015-06-07","nightly":29,"aurora":30,"beta":1946,"release":644},{"date":"2015-06-08","nightly":44,"aurora":40,"beta":2436,"release":1149},{"date":"2015-06-09","nightly":22,"aurora":37,"beta":2727,"release":1206},{"date":"2015-06-10","nightly":34,"aurora":204,"beta":2426,"release":1193},{"date":"2015-06-11","nightly":25,"aurora":141,"beta":1804,"release":1304},{"date":"2015-06-12","nightly":10,"aurora":32,"beta":1074,"release":1117},{"date":"2015-06-13","nightly":13,"aurora":44,"beta":826,"release":925},{"date":"2015-06-14","nightly":21,"aurora":36,"beta":700,"release":856},{"date":"2015-06-15","nightly":16,"aurora":28,"beta":921,"release":1390},{"date":"2015-06-16","nightly":18,"aurora":65,"beta":927,"release":1373},{"date":"2015-06-17","nightly":15,"aurora":35,"beta":864,"release":1343},{"date":"2015-06-18","nightly":10,"aurora":15,"beta":759,"release":1350},{"date":"2015-06-19","nightly":4,"aurora":20,"beta":671,"release":1268},{"date":"2015-06-20","nightly":3,"aurora":5,"beta":591,"release":866},{"date":"2015-06-21","nightly":12,"aurora":8,"beta":549,"release":869},{"date":"2015-06-22","nightly":8,"aurora":29,"beta":733,"release":1307},{"date":"2015-06-23","nightly":3,"aurora":14,"beta":837,"release":1393},{"date":"2015-06-24","nightly":7,"aurora":11,"beta":746,"release":1233},{"date":"2015-06-25","nightly":29,"aurora":11,"beta":626,"release":1224},{"date":"2015-06-26","nightly":13,"aurora":12,"beta":632,"release":1162},{"date":"2015-06-27","nightly":2,"aurora":28,"beta":514,"release":745},{"date":"2015-06-28","nightly":3,"aurora":7,"beta":499,"release":703},{"date":"2015-06-29","nightly":0,"aurora":7,"beta":641,"release":1221},{"date":"2015-06-30","nightly":11,"aurora":8,"beta":671,"release":1194},{"date":"2015-07-01","nightly":5,"aurora":11,"beta":576,"release":1120},{"date":"2015-07-02","nightly":9,"aurora":8,"beta":608,"release":1106},{"date":"2015-07-03","nightly":3,"aurora":13,"beta":583,"release":1077},{"date":"2015-07-04","nightly":3,"aurora":10,"beta":475,"release":678},{"date":"2015-07-05","nightly":6,"aurora":7,"beta":316,"release":650},{"date":"2015-07-06","nightly":8,"aurora":12,"beta":529,"release":1112},{"date":"2015-07-07","nightly":3,"aurora":15,"beta":483,"release":1036},{"date":"2015-07-08","nightly":1,"aurora":12,"beta":539,"release":1103},{"date":"2015-07-09","nightly":5,"aurora":14,"beta":616,"release":1101},{"date":"2015-07-10","nightly":2,"aurora":18,"beta":518,"release":1001},{"date":"2015-07-11","nightly":6,"aurora":7,"beta":378,"release":715},{"date":"2015-07-12","nightly":3,"aurora":9,"beta":349,"release":651},{"date":"2015-07-13","nightly":9,"aurora":16,"beta":494,"release":1169},{"date":"2015-07-14","nightly":11,"aurora":9,"beta":525,"release":1116},{"date":"2015-07-15","nightly":16,"aurora":20,"beta":451,"release":1099},{"date":"2015-07-16","nightly":14,"aurora":21,"beta":415,"release":1124},{"date":"2015-07-17","nightly":10,"aurora":7,"beta":416,"release":933},{"date":"2015-07-18","nightly":19,"aurora":5,"beta":307,"release":622},{"date":"2015-07-19","nightly":14,"aurora":8,"beta":290,"release":635},{"date":"2015-07-20","nightly":22,"aurora":10,"beta":442,"release":1146},{"date":"2015-07-21","nightly":24,"aurora":4,"beta":462,"release":1147},{"date":"2015-07-22","nightly":17,"aurora":10,"beta":499,"release":1105},{"date":"2015-07-23","nightly":12,"aurora":16,"beta":529,"release":1036},{"date":"2015-07-24","nightly":7,"aurora":7,"beta":452,"release":979},{"date":"2015-07-25","nightly":11,"aurora":11,"beta":341,"release":701},{"date":"2015-07-26","nightly":2,"aurora":10,"beta":333,"release":595},{"date":"2015-07-27","nightly":9,"aurora":6,"beta":436,"release":1126},{"date":"2015-07-28","nightly":5,"aurora":12,"beta":478,"release":1117},{"date":"2015-07-29","nightly":18,"aurora":10,"beta":447,"release":1122},{"date":"2015-07-30","nightly":8,"aurora":9,"beta":443,"release":1146},{"date":"2015-07-31","nightly":2,"aurora":15,"beta":452,"release":986},{"date":"2015-08-01","nightly":4,"aurora":5,"beta":313,"release":609},{"date":"2015-08-02","nightly":3,"aurora":8,"beta":307,"release":554},{"date":"2015-08-03","nightly":4,"aurora":12,"beta":420,"release":1033},{"date":"2015-08-04","nightly":3,"aurora":18,"beta":476,"release":1059},{"date":"2015-08-05","nightly":6,"aurora":19,"beta":446,"release":1035},{"date":"2015-08-06","nightly":4,"aurora":19,"beta":440,"release":1068},{"date":"2015-08-07","nightly":4,"aurora":14,"beta":442,"release":1087},{"date":"2015-08-08","nightly":6,"aurora":9,"beta":319,"release":619},{"date":"2015-08-09","nightly":3,"aurora":9,"beta":279,"release":654},{"date":"2015-08-10","nightly":8,"aurora":13,"beta":549,"release":1115},{"date":"2015-08-11","nightly":5,"aurora":10,"beta":431,"release":1186},{"date":"2015-08-12","nightly":6,"aurora":10,"beta":414,"release":1134},{"date":"2015-08-13","nightly":3,"aurora":6,"beta":375,"release":1064},{"date":"2015-08-14","nightly":5,"aurora":10,"beta":361,"release":904},{"date":"2015-08-15","nightly":6,"aurora":7,"beta":339,"release":537},{"date":"2015-08-16","nightly":5,"aurora":6,"beta":249,"release":519},{"date":"2015-08-17","nightly":6,"aurora":20,"beta":361,"release":906},{"date":"2015-08-18","nightly":5,"aurora":14,"beta":483,"release":899},{"date":"2015-08-19","nightly":5,"aurora":9,"beta":504,"release":984},{"date":"2015-08-20","nightly":16,"aurora":13,"beta":423,"release":884},{"date":"2015-08-21","nightly":3,"aurora":12,"beta":542,"release":754},{"date":"2015-08-22","nightly":1,"aurora":14,"beta":356,"release":579},{"date":"2015-08-23","nightly":1,"aurora":7,"beta":287,"release":510},{"date":"2015-08-24","nightly":2,"aurora":23,"beta":544,"release":925},{"date":"2015-08-25","nightly":4,"aurora":18,"beta":499,"release":981},{"date":"2015-08-26","nightly":6,"aurora":24,"beta":457,"release":911},{"date":"2015-08-27","nightly":1,"aurora":17,"beta":505,"release":993},{"date":"2015-08-28","nightly":7,"aurora":12,"beta":465,"release":932},{"date":"2015-08-29","nightly":4,"aurora":7,"beta":359,"release":590},{"date":"2015-08-30","nightly":1,"aurora":16,"beta":347,"release":610},{"date":"2015-08-31","nightly":3,"aurora":10,"beta":510,"release":1024},{"date":"2015-09-01","nightly":3,"aurora":11,"beta":552,"release":953},{"date":"2015-09-02","nightly":5,"aurora":25,"beta":583,"release":911},{"date":"2015-09-03","nightly":3,"aurora":15,"beta":614,"release":1011},{"date":"2015-09-04","nightly":1,"aurora":15,"beta":478,"release":913},{"date":"2015-09-05","nightly":2,"aurora":10,"beta":563,"release":598},{"date":"2015-09-06","nightly":2,"aurora":18,"beta":607,"release":609},{"date":"2015-09-07","nightly":5,"aurora":13,"beta":772,"release":885},{"date":"2015-09-08","nightly":0,"aurora":12,"beta":790,"release":1015},{"date":"2015-09-09","nightly":4,"aurora":10,"beta":739,"release":1051},{"date":"2015-09-10","nightly":5,"aurora":15,"beta":703,"release":963},{"date":"2015-09-11","nightly":2,"aurora":18,"beta":675,"release":920},{"date":"2015-09-12","nightly":2,"aurora":4,"beta":435,"release":604},{"date":"2015-09-13","nightly":1,"aurora":18,"beta":416,"release":604},{"date":"2015-09-14","nightly":7,"aurora":21,"beta":625,"release":1016},{"date":"2015-09-15","nightly":0,"aurora":11,"beta":582,"release":1196},{"date":"2015-09-16","nightly":1,"aurora":18,"beta":599,"release":1040},{"date":"2015-09-17","nightly":1,"aurora":6,"beta":542,"release":1038},{"date":"2015-09-18","nightly":5,"aurora":12,"beta":536,"release":986},{"date":"2015-09-19","nightly":0,"aurora":6,"beta":450,"release":682},{"date":"2015-09-20","nightly":6,"aurora":5,"beta":341,"release":621},{"date":"2015-09-21","nightly":4,"aurora":11,"beta":599,"release":1016},{"date":"2015-09-22","nightly":2,"aurora":11,"beta":538,"release":1054},{"date":"2015-09-23","nightly":1,"aurora":16,"beta":590,"release":1220},{"date":"2015-09-24","nightly":3,"aurora":15,"beta":464,"release":1300},{"date":"2015-09-25","nightly":2,"aurora":6,"beta":569,"release":1416},{"date":"2015-09-26","nightly":2,"aurora":5,"beta":530,"release":1071},{"date":"2015-09-27","nightly":4,"aurora":11,"beta":514,"release":1076},{"date":"2015-09-28","nightly":12,"aurora":10,"beta":688,"release":1456},{"date":"2015-09-29","nightly":2,"aurora":12,"beta":792,"release":1720},{"date":"2015-09-30","nightly":1,"aurora":9,"beta":927,"release":1785},{"date":"2015-10-01","nightly":2,"aurora":8,"beta":875,"release":1647},{"date":"2015-10-02","nightly":1,"aurora":10,"beta":723,"release":1514},{"date":"2015-10-03","nightly":9,"aurora":7,"beta":691,"release":1610},{"date":"2015-10-04","nightly":0,"aurora":11,"beta":585,"release":1893},{"date":"2015-10-05","nightly":2,"aurora":5,"beta":865,"release":2312},{"date":"2015-10-06","nightly":5,"aurora":10,"beta":847,"release":2604},{"date":"2015-10-07","nightly":0,"aurora":5,"beta":834,"release":2563},{"date":"2015-10-08","nightly":0,"aurora":7,"beta":845,"release":2592},{"date":"2015-10-09","nightly":2,"aurora":10,"beta":799,"release":2512},{"date":"2015-10-10","nightly":0,"aurora":4,"beta":681,"release":1958},{"date":"2015-10-11","nightly":3,"aurora":8,"beta":633,"release":1876},{"date":"2015-10-12","nightly":0,"aurora":5,"beta":841,"release":2479},{"date":"2015-10-13","nightly":1,"aurora":8,"beta":802,"release":2558},{"date":"2015-10-14","nightly":3,"aurora":22,"beta":796,"release":2528},{"date":"2015-10-15","nightly":12,"aurora":13,"beta":812,"release":2303},{"date":"2015-10-16","nightly":3,"aurora":6,"beta":789,"release":2390},{"date":"2015-10-17","nightly":2,"aurora":7,"beta":739,"release":1993},{"date":"2015-10-18","nightly":2,"aurora":6,"beta":573,"release":1932},{"date":"2015-10-19","nightly":3,"aurora":16,"beta":709,"release":2511},{"date":"2015-10-20","nightly":3,"aurora":4,"beta":779,"release":2635},{"date":"2015-10-21","nightly":1,"aurora":6,"beta":793,"release":2592},{"date":"2015-10-22","nightly":1,"aurora":8,"beta":675,"release":2379},{"date":"2015-10-23","nightly":1,"aurora":4,"beta":669,"release":2383},{"date":"2015-10-24","nightly":2,"aurora":13,"beta":510,"release":1780},{"date":"2015-10-25","nightly":4,"aurora":5,"beta":533,"release":1806},{"date":"2015-10-26","nightly":2,"aurora":18,"beta":747,"release":2435},{"date":"2015-10-27","nightly":2,"aurora":10,"beta":778,"release":2464},{"date":"2015-10-28","nightly":11,"aurora":9,"beta":700,"release":2437},{"date":"2015-10-29","nightly":198,"aurora":10,"beta":809,"release":2511},{"date":"2015-10-30","nightly":98,"aurora":20,"beta":758,"release":2433},{"date":"2015-10-31","nightly":110,"aurora":16,"beta":541,"release":1865},{"date":"2015-11-01","nightly":104,"aurora":6,"beta":453,"release":1669},{"date":"2015-11-02","nightly":103,"aurora":12,"beta":653,"release":2154},{"date":"2015-11-03","nightly":78,"aurora":31,"beta":700,"release":2249},{"date":"2015-11-04","nightly":39,"aurora":49,"beta":675,"release":2353},{"date":"2015-11-05","nightly":85,"aurora":30,"beta":766,"release":2539},{"date":"2015-11-06","nightly":85,"aurora":18,"beta":656,"release":2381},{"date":"2015-11-07","nightly":42,"aurora":24,"beta":589,"release":2116},{"date":"2015-11-08","nightly":29,"aurora":30,"beta":516,"release":1973},{"date":"2015-11-09","nightly":33,"aurora":28,"beta":721,"release":2636},{"date":"2015-11-10","nightly":48,"aurora":19,"beta":742,"release":2704},{"date":"2015-11-11","nightly":13,"aurora":21,"beta":718,"release":2505},{"date":"2015-11-12","nightly":8,"aurora":22,"beta":746,"release":2665},{"date":"2015-11-13","nightly":14,"aurora":28,"beta":666,"release":2501},{"date":"2015-11-14","nightly":13,"aurora":16,"beta":502,"release":1858},{"date":"2015-11-15","nightly":9,"aurora":12,"beta":449,"release":1805}]
